tronlinknet/__init__.py
tronlinknet/main.py
tronlinknet-0.1.0.dist-info/LICENSE.txt
tronlinknet-0.1.0.dist-info/METADATA
tronlinknet-0.1.0.dist-info/WHEEL
tronlinknet-0.1.0.dist-info/top_level.txt
tronlinknet-0.1.0.dist-info/RECORD
