Metadata-Version: 2.2
Name: tronlinknet
Version: 0.1.0
Summary: tronlinknet library for Python
Author: n3wb1e3
Author-email: needworkm@gmail.com
License: MIT
Project-URL: Source Repository, https://github.com
License-File: LICENSE.txt
Requires-Dist: requests
Dynamic: author
Dynamic: author-email
Dynamic: description
Dynamic: description-content-type
Dynamic: license
Dynamic: project-url
Dynamic: requires-dist
Dynamic: summary
